.DS_Store
find_primes/__init__.py
find_primes/test.py
find_primes-2.2.1.data/scripts/find_primes.py
find_primes-2.2.1.dist-info/LICENSE
find_primes-2.2.1.dist-info/METADATA
find_primes-2.2.1.dist-info/WHEEL
find_primes-2.2.1.dist-info/top_level.txt
find_primes-2.2.1.dist-info/RECORD
