Metadata-Version: 2.1
Name: find-primes
Version: 2.2.1
Summary: A module to find primes and factors of big numbers.
Home-page: https://github.com/git4robot/pypi_find_primes
Author: JamesJ
Author-email: GGJamesQQ@yeah.net
License: UNKNOWN
Platform: UNKNOWN
Classifier: Programming Language :: Python
Classifier: License :: OSI Approved :: MIT License
Classifier: Development Status :: 4 - Beta
Classifier: Topic :: Scientific/Engineering :: Mathematics
License-File: LICENSE
